.gitignore
AUTHORS.rst
CONTRIBUTING.rst
COPYING.txt
FAQ.rst
MANIFEST.in
NEWS.rst
README.rst
TODO.org
TODO.org_archive
setup.py
examples/eval_m_file.py
examples/fir_filter.py
examples/my_script.m
examples/print_version.py
examples/random_plot.py
examples/playground/sandbox.py
examples/playground/sandbox_cells.py
examples/playground/sandbox_struct.py
matlab_wrapper/__init__.py
matlab_wrapper/matlab_session.py
matlab_wrapper/typeconv.py
matlab_wrapper.egg-info/PKG-INFO
matlab_wrapper.egg-info/SOURCES.txt
matlab_wrapper.egg-info/dependency_links.txt
matlab_wrapper.egg-info/requires.txt
matlab_wrapper.egg-info/top_level.txt
tests/test_matlab.py
tests/leak_loops/putget_loop.py
tests/leak_loops/restart_loop.py