Metadata-Version: 1.1
Name: matlab-wrapper
Version: 1
Summary: MATLAB wrapper for Python
Home-page: https://github.com/mrkrd/matlab_wrapper
Author: Marek Rudnicki
Author-email: marekrud@posteo.de
License: GPLv3
Download-URL: https://github.com/mrkrd/matlab_wrapper/tarball/master
Platform: Linux
Platform: Windows
Platform: OSX
Classifier: Development Status :: 4 - Beta
Classifier: Environment :: Console
Classifier: Intended Audience :: End Users/Desktop
Classifier: Intended Audience :: Science/Research
Classifier: License :: OSI Approved :: GNU General Public License v3 or later (GPLv3+)
Classifier: Operating System :: POSIX
Classifier: Operating System :: POSIX :: Linux
Classifier: Operating System :: Microsoft :: Windows
Classifier: Operating System :: MacOS :: MacOS X
Classifier: Programming Language :: Python
Classifier: Programming Language :: Python :: 2
Classifier: Programming Language :: Python :: 2.7
